matrixdifferential
