Metadata-Version: 1.0
Name: matrixdifferential
Version: 0.0.12
Summary: This is a mathematic calculation package for computing matrix differential
Home-page: https://github.com/Bertie97/pyctlib/tree/main/pyctlib
Author: All contributors of PyCTLib
Author-email: zytfdu@icloud.com
License: MIT Licence
Keywords: pip,pyctlib
Platform: any
